group_slip/__init__.py
group_slip/cfuns/__init__.py
group_slip/cfuns/image_scanner.py
group_slip/cfuns/ocr_and_group.py
group_slip/main.py
group_slip-1.1.1.dist-info/entry_points.txt
group_slip-1.1.1.dist-info/METADATA
group_slip-1.1.1.dist-info/WHEEL
group_slip-1.1.1.dist-info/RECORD
